{
  "data-path": "/home/hdvries/data/prep_128.txt",
  "max-position-embeddings": "512",
  "max-seq-length": "128",
  "num-layers": "24",
  "hidden-size": "1024",
  "intermediate-size": "4096",
  "num-attention-heads": "16",
  "hidden-dropout": "0.1",
  "attention-dropout": "0.1",
  "train-iters": "1000000",
  "report-every": "100",
  "save-every": "10000",
  "num-workers": "1",
  "learning-rate": "1e-4",
  "warmup-proportion": "0.01",
  "weight-decay": "0.01",
  "max-grad-norm": "1.0",
  "batch-size": "20",
  "use-fp16": "",
  "layernorm-fp32": "",
  "checkpoint-act-fn": ""
}
